{
	"showSidebar": true,
	"sidebar": {
		"text": "The human-centered, data-driven, technically empowered product manager"
	},
	"content": {
		"title": "Hi! I'm Rashan.",
		"class": "home",
		"subtitle": "The human-centered, data-driven, technically empowered product manager",
		"elements": [
			{
				"title": "Stuff I Worked On",
				"url": "#portfolio",
				"id": "portfolio",
				"icon": "portfolio_white.png"
			},
			{
				"title": "Tech Stack",
				"url": "#techstack",
				"id": "techstack",
				"icon": "tools_white.png"
			},
			{
				"title": "Interesting Code",
				"url": "#code",
				"id": "code",
				"icon": "code_white.png"
			},
			{
				"title": "Writings",
				"url": "#articles",
				"id": "articles",
				"icon": "article_white.png"
			},
			{
				"title": "Presentations",
				"url": "#presentations",
				"id": "presentations",
				"icon": "presentation_white.png"
			}
		]
	}
}
